private_attrs.py
private_attrs-1.0.1.dist-info/LICENSE
private_attrs-1.0.1.dist-info/METADATA
private_attrs-1.0.1.dist-info/WHEEL
private_attrs-1.0.1.dist-info/top_level.txt
private_attrs-1.0.1.dist-info/zip-safe
private_attrs-1.0.1.dist-info/RECORD
