Metadata-Version: 2.1
Name: private-attrs
Version: 1.0.1
Summary: This module provides support for easy addition of private attributes inside your custom objects, which are totally unreachable from outside the class definition, as in C++ 'private' clause.
Home-page: https://github.com/fernandoenzo/private-attrs/
Download-URL: https://github.com/fernandoenzo/private-attrs/
Author: Fernando Enzo Guarini
Author-email: fernandoenzo@gmail.com
License: GPLv3+
Project-URL: Source, https://github.com/fernandoenzo/private-attrs/
Keywords: attr attribute private static
Platform: UNKNOWN
Classifier: Development Status :: 5 - Production/Stable
Classifier: Intended Audience :: Developers
Classifier: License :: OSI Approved :: GNU General Public License v3 or later (GPLv3+)
Classifier: Operating System :: POSIX
Classifier: Programming Language :: Python :: 3 :: Only
Classifier: Programming Language :: Python :: 3.7
Classifier: Programming Language :: Python :: 3.8
Classifier: Programming Language :: Python :: 3.9
Classifier: Programming Language :: Python :: 3.10
Classifier: Topic :: Software Development :: Libraries :: Python Modules
Requires-Python: >=3.7
License-File: LICENSE
